stablerandom/__init__.py
stablerandom/stablerandom.py
stablerandom/stablerandom_test.py
stablerandom-0.10.46.dist-info/LICENSE.txt
stablerandom-0.10.46.dist-info/METADATA
stablerandom-0.10.46.dist-info/WHEEL
stablerandom-0.10.46.dist-info/RECORD
