Metadata-Version: 2.3
Name: stablerandom
Version: 0.10.46
Summary: Create stable/repeatable numpy.random applications
Author: John Heintz
Author-email: john@gistlabs.com
Requires-Python: >=3.10,<4.0
Classifier: Programming Language :: Python :: 3
Classifier: Programming Language :: Python :: 3.10
Classifier: Programming Language :: Python :: 3.11
Classifier: Programming Language :: Python :: 3.12
Classifier: Programming Language :: Python :: 3.13
Requires-Dist: numpy (>=2.0,<3.0)
